maxpreps_scraper/__init__.py
maxpreps_scraper/scraper.py
maxpreps_scraper-0.1.2.dist-info/LICENSE
maxpreps_scraper-0.1.2.dist-info/METADATA
maxpreps_scraper-0.1.2.dist-info/WHEEL
maxpreps_scraper-0.1.2.dist-info/top_level.txt
maxpreps_scraper-0.1.2.dist-info/RECORD
