Metadata-Version: 2.2
Name: maxpreps-scraper
Version: 0.1.2
Summary: A Python scraper for MaxPreps high school sports data
Home-page: https://github.com/raghavdhir03/maxpreps_scraper
Author: Raghav Dhir
Author-email: dhir.raghav@gmail.com
Classifier: Programming Language :: Python :: 3
Classifier: License :: OSI Approved :: MIT License
Classifier: Operating System :: OS Independent
Requires-Python: >=3.7
License-File: LICENSE
Requires-Dist: requests
Requires-Dist: beautifulsoup4
Requires-Dist: tqdm
Requires-Dist: pandas
Requires-Dist: lxml
Requires-Dist: html5lib
Dynamic: author
Dynamic: author-email
Dynamic: classifier
Dynamic: description
Dynamic: description-content-type
Dynamic: home-page
Dynamic: requires-dist
Dynamic: requires-python
Dynamic: summary
